<?xml version="1.0" encoding="UTF-8"?>
<export version="E">
  <design>
    <source>/home/anilv/kicad/stm32-breakout/stm32-breakout.kicad_sch</source>
    <date>Paz 06 Ağu 2023 10:35:02</date>
    <tool>Eeschema 7.0.6-1.fc38</tool>
    <sheet number="1" name="/" tstamps="/">
      <title_block>
        <title>STM32F103C8T6</title>
        <company>https://github.com/anilv8</company>
        <rev>v.1.0</rev>
        <date>2023-08-04</date>
        <source>stm32-breakout.kicad_sch</source>
        <comment number="1" value=""/>
        <comment number="2" value=""/>
        <comment number="3" value=""/>
        <comment number="4" value=""/>
        <comment number="5" value=""/>
        <comment number="6" value=""/>
        <comment number="7" value=""/>
        <comment number="8" value=""/>
        <comment number="9" value=""/>
      </title_block>
    </sheet>
  </design>
  <components>
    <comp ref="C1">
      <value>1u</value>
      <footprint>Capacitor_SMD:C_0603_1608Metric</footprint>
      <libsource lib="Device" part="C" description="Unpolarized capacitor"/>
      <property name="Sheetname" value=""/>
      <property name="Sheetfile" value="stm32-breakout.kicad_sch"/>
      <property name="ki_description" value="Unpolarized capacitor"/>
      <property name="ki_keywords" value="cap capacitor"/>
      <sheetpath names="/" tstamps="/"/>
      <tstamps>087f50e4-7b5d-4702-b84c-f11ea5a7d76c</tstamps>
    </comp>
    <comp ref="C2">
      <value>1u</value>
      <footprint>Capacitor_SMD:C_0603_1608Metric</footprint>
      <libsource lib="Device" part="C" description="Unpolarized capacitor"/>
      <property name="Sheetname" value=""/>
      <property name="Sheetfile" value="stm32-breakout.kicad_sch"/>
      <property name="ki_description" value="Unpolarized capacitor"/>
      <property name="ki_keywords" value="cap capacitor"/>
      <sheetpath names="/" tstamps="/"/>
      <tstamps>881df737-b6d8-453b-8bfa-ce806d9ec327</tstamps>
    </comp>
    <comp ref="C3">
      <value>4u7</value>
      <footprint>Capacitor_SMD:C_0603_1608Metric</footprint>
      <libsource lib="Device" part="C" description="Unpolarized capacitor"/>
      <property name="Sheetname" value=""/>
      <property name="Sheetfile" value="stm32-breakout.kicad_sch"/>
      <property name="ki_description" value="Unpolarized capacitor"/>
      <property name="ki_keywords" value="cap capacitor"/>
      <sheetpath names="/" tstamps="/"/>
      <tstamps>58a3d105-4b1c-4f97-8cfe-c560104c6312</tstamps>
    </comp>
    <comp ref="C4">
      <value>100n</value>
      <footprint>Capacitor_SMD:C_0402_1005Metric</footprint>
      <libsource lib="Device" part="C" description="Unpolarized capacitor"/>
      <property name="Sheetname" value=""/>
      <property name="Sheetfile" value="stm32-breakout.kicad_sch"/>
      <property name="ki_description" value="Unpolarized capacitor"/>
      <property name="ki_keywords" value="cap capacitor"/>
      <sheetpath names="/" tstamps="/"/>
      <tstamps>980c605a-2c61-4aa3-a5a5-afede8ff0d07</tstamps>
    </comp>
    <comp ref="C5">
      <value>100n</value>
      <footprint>Capacitor_SMD:C_0402_1005Metric</footprint>
      <libsource lib="Device" part="C" description="Unpolarized capacitor"/>
      <property name="Sheetname" value=""/>
      <property name="Sheetfile" value="stm32-breakout.kicad_sch"/>
      <property name="ki_description" value="Unpolarized capacitor"/>
      <property name="ki_keywords" value="cap capacitor"/>
      <sheetpath names="/" tstamps="/"/>
      <tstamps>996fd33c-b95a-4314-bd66-cf47bdb796ce</tstamps>
    </comp>
    <comp ref="C6">
      <value>100n</value>
      <footprint>Capacitor_SMD:C_0402_1005Metric</footprint>
      <libsource lib="Device" part="C" description="Unpolarized capacitor"/>
      <property name="Sheetname" value=""/>
      <property name="Sheetfile" value="stm32-breakout.kicad_sch"/>
      <property name="ki_description" value="Unpolarized capacitor"/>
      <property name="ki_keywords" value="cap capacitor"/>
      <sheetpath names="/" tstamps="/"/>
      <tstamps>0feff862-e72e-4ab4-8bc7-02bb3fae2be9</tstamps>
    </comp>
    <comp ref="C7">
      <value>100n</value>
      <footprint>Capacitor_SMD:C_0402_1005Metric</footprint>
      <libsource lib="Device" part="C" description="Unpolarized capacitor"/>
      <property name="Sheetname" value=""/>
      <property name="Sheetfile" value="stm32-breakout.kicad_sch"/>
      <property name="ki_description" value="Unpolarized capacitor"/>
      <property name="ki_keywords" value="cap capacitor"/>
      <sheetpath names="/" tstamps="/"/>
      <tstamps>b4f18bb2-c676-4201-bf13-b820a38880a4</tstamps>
    </comp>
    <comp ref="C8">
      <value>1u</value>
      <footprint>Capacitor_SMD:C_0402_1005Metric</footprint>
      <libsource lib="Device" part="C" description="Unpolarized capacitor"/>
      <property name="Sheetname" value=""/>
      <property name="Sheetfile" value="stm32-breakout.kicad_sch"/>
      <property name="ki_description" value="Unpolarized capacitor"/>
      <property name="ki_keywords" value="cap capacitor"/>
      <sheetpath names="/" tstamps="/"/>
      <tstamps>ba103db4-1356-4f64-9c2b-420855930822</tstamps>
    </comp>
    <comp ref="C9">
      <value>100n</value>
      <footprint>Capacitor_SMD:C_0402_1005Metric</footprint>
      <libsource lib="Device" part="C" description="Unpolarized capacitor"/>
      <property name="Sheetname" value=""/>
      <property name="Sheetfile" value="stm32-breakout.kicad_sch"/>
      <property name="ki_description" value="Unpolarized capacitor"/>
      <property name="ki_keywords" value="cap capacitor"/>
      <sheetpath names="/" tstamps="/"/>
      <tstamps>0273aa79-27ef-4e90-9c76-2729035fe4f3</tstamps>
    </comp>
    <comp ref="C10">
      <value>30p</value>
      <footprint>Capacitor_SMD:C_0402_1005Metric</footprint>
      <libsource lib="Device" part="C" description="Unpolarized capacitor"/>
      <property name="Sheetname" value=""/>
      <property name="Sheetfile" value="stm32-breakout.kicad_sch"/>
      <property name="ki_description" value="Unpolarized capacitor"/>
      <property name="ki_keywords" value="cap capacitor"/>
      <sheetpath names="/" tstamps="/"/>
      <tstamps>1176e748-566e-487a-8d52-40b691e050f4</tstamps>
    </comp>
    <comp ref="C11">
      <value>30p</value>
      <footprint>Capacitor_SMD:C_0402_1005Metric</footprint>
      <libsource lib="Device" part="C" description="Unpolarized capacitor"/>
      <property name="Sheetname" value=""/>
      <property name="Sheetfile" value="stm32-breakout.kicad_sch"/>
      <property name="ki_description" value="Unpolarized capacitor"/>
      <property name="ki_keywords" value="cap capacitor"/>
      <sheetpath names="/" tstamps="/"/>
      <tstamps>511ca31c-460d-4710-bfc1-014e861df16a</tstamps>
    </comp>
    <comp ref="D1">
      <value>GREEN</value>
      <footprint>LED_SMD:LED_0603_1608Metric</footprint>
      <libsource lib="Device" part="LED_Small" description="Light emitting diode, small symbol"/>
      <property name="Sheetname" value=""/>
      <property name="Sheetfile" value="stm32-breakout.kicad_sch"/>
      <property name="ki_description" value="Light emitting diode, small symbol"/>
      <property name="ki_keywords" value="LED diode light-emitting-diode"/>
      <sheetpath names="/" tstamps="/"/>
      <tstamps>5c9849c6-9a5d-4ba3-9c95-3250f387f229</tstamps>
    </comp>
    <comp ref="D2">
      <value>BLUE</value>
      <footprint>LED_SMD:LED_0603_1608Metric</footprint>
      <libsource lib="Device" part="LED_Small" description="Light emitting diode, small symbol"/>
      <property name="Sheetname" value=""/>
      <property name="Sheetfile" value="stm32-breakout.kicad_sch"/>
      <property name="ki_description" value="Light emitting diode, small symbol"/>
      <property name="ki_keywords" value="LED diode light-emitting-diode"/>
      <sheetpath names="/" tstamps="/"/>
      <tstamps>7b313e41-21c3-4f6f-a8f7-e8da5a358154</tstamps>
    </comp>
    <comp ref="FB1">
      <value>100R</value>
      <footprint>Inductor_SMD:L_0805_2012Metric</footprint>
      <libsource lib="Device" part="FerriteBead" description="Ferrite bead"/>
      <property name="Sheetname" value=""/>
      <property name="Sheetfile" value="stm32-breakout.kicad_sch"/>
      <property name="ki_description" value="Ferrite bead"/>
      <property name="ki_keywords" value="L ferrite bead inductor filter"/>
      <sheetpath names="/" tstamps="/"/>
      <tstamps>00906376-04ab-4bf1-a34d-ef238ca73eb8</tstamps>
    </comp>
    <comp ref="H1">
      <value>MountingHole</value>
      <footprint>MountingHole:MountingHole_2.2mm_M2</footprint>
      <libsource lib="Mechanical" part="MountingHole" description="Mounting Hole without connection"/>
      <property name="Sheetname" value=""/>
      <property name="Sheetfile" value="stm32-breakout.kicad_sch"/>
      <property name="ki_description" value="Mounting Hole without connection"/>
      <property name="ki_keywords" value="mounting hole"/>
      <sheetpath names="/" tstamps="/"/>
      <tstamps>4e77a979-e1a2-439e-adb5-1ce663f90ee1</tstamps>
    </comp>
    <comp ref="H2">
      <value>MountingHole</value>
      <footprint>MountingHole:MountingHole_2.2mm_M2</footprint>
      <libsource lib="Mechanical" part="MountingHole" description="Mounting Hole without connection"/>
      <property name="Sheetname" value=""/>
      <property name="Sheetfile" value="stm32-breakout.kicad_sch"/>
      <property name="ki_description" value="Mounting Hole without connection"/>
      <property name="ki_keywords" value="mounting hole"/>
      <sheetpath names="/" tstamps="/"/>
      <tstamps>d2606b84-d4a3-41f0-a24b-2ab92b275d82</tstamps>
    </comp>
    <comp ref="H3">
      <value>MountingHole</value>
      <footprint>MountingHole:MountingHole_2.2mm_M2</footprint>
      <libsource lib="Mechanical" part="MountingHole" description="Mounting Hole without connection"/>
      <property name="Sheetname" value=""/>
      <property name="Sheetfile" value="stm32-breakout.kicad_sch"/>
      <property name="ki_description" value="Mounting Hole without connection"/>
      <property name="ki_keywords" value="mounting hole"/>
      <sheetpath names="/" tstamps="/"/>
      <tstamps>7e89c57b-0ceb-4ca1-8a1e-5ce8bc8d345a</tstamps>
    </comp>
    <comp ref="H4">
      <value>MountingHole</value>
      <footprint>MountingHole:MountingHole_2.2mm_M2</footprint>
      <libsource lib="Mechanical" part="MountingHole" description="Mounting Hole without connection"/>
      <property name="Sheetname" value=""/>
      <property name="Sheetfile" value="stm32-breakout.kicad_sch"/>
      <property name="ki_description" value="Mounting Hole without connection"/>
      <property name="ki_keywords" value="mounting hole"/>
      <sheetpath names="/" tstamps="/"/>
      <tstamps>d790827a-35ba-411e-8cef-a6a4795ccbe5</tstamps>
    </comp>
    <comp ref="J1">
      <value>USB_B_Micro</value>
      <footprint>Connector_USB:USB_Micro-B_Wuerth_629105150521</footprint>
      <libsource lib="Connector" part="USB_B_Micro" description="USB Micro Type B connector"/>
      <property name="Sheetname" value=""/>
      <property name="Sheetfile" value="stm32-breakout.kicad_sch"/>
      <property name="ki_description" value="USB Micro Type B connector"/>
      <property name="ki_keywords" value="connector USB micro"/>
      <sheetpath names="/" tstamps="/"/>
      <tstamps>1fde09ee-0a2f-47ad-a64c-57719c89a374</tstamps>
    </comp>
    <comp ref="J2">
      <value>Conn_01x15</value>
      <footprint>Connector_PinHeader_2.54mm:PinHeader_1x15_P2.54mm_Vertical</footprint>
      <libsource lib="Connector_Generic" part="Conn_01x15" description="Generic connector, single row, 01x15, script generated (kicad-library-utils/schlib/autogen/connector/)"/>
      <property name="Sheetname" value=""/>
      <property name="Sheetfile" value="stm32-breakout.kicad_sch"/>
      <property name="ki_description" value="Generic connector, single row, 01x15, script generated (kicad-library-utils/schlib/autogen/connector/)"/>
      <property name="ki_keywords" value="connector"/>
      <sheetpath names="/" tstamps="/"/>
      <tstamps>bdaf3905-200f-4e6b-9cfc-e8c9f7462848</tstamps>
    </comp>
    <comp ref="J3">
      <value>Conn_01x15</value>
      <footprint>Connector_PinHeader_2.54mm:PinHeader_1x15_P2.54mm_Vertical</footprint>
      <libsource lib="Connector_Generic" part="Conn_01x15" description="Generic connector, single row, 01x15, script generated (kicad-library-utils/schlib/autogen/connector/)"/>
      <property name="Sheetname" value=""/>
      <property name="Sheetfile" value="stm32-breakout.kicad_sch"/>
      <property name="ki_description" value="Generic connector, single row, 01x15, script generated (kicad-library-utils/schlib/autogen/connector/)"/>
      <property name="ki_keywords" value="connector"/>
      <sheetpath names="/" tstamps="/"/>
      <tstamps>a9bf3a08-e678-4aed-ac4a-b743b2fd2d27</tstamps>
    </comp>
    <comp ref="JP1">
      <value>SolderJumper_2_Open</value>
      <footprint>Jumper:SolderJumper-2_P1.3mm_Open_Pad1.0x1.5mm</footprint>
      <libsource lib="Jumper" part="SolderJumper_2_Open" description="Solder Jumper, 2-pole, open"/>
      <property name="Sheetname" value=""/>
      <property name="Sheetfile" value="stm32-breakout.kicad_sch"/>
      <property name="ki_description" value="Solder Jumper, 2-pole, open"/>
      <property name="ki_keywords" value="solder jumper SPST"/>
      <sheetpath names="/" tstamps="/"/>
      <tstamps>02ad55e8-f82e-4c7c-a34b-8dcc51f49548</tstamps>
    </comp>
    <comp ref="L1">
      <value>27n</value>
      <footprint>Inductor_SMD:L_0402_1005Metric</footprint>
      <libsource lib="Device" part="L" description="Inductor"/>
      <property name="Sheetname" value=""/>
      <property name="Sheetfile" value="stm32-breakout.kicad_sch"/>
      <property name="ki_description" value="Inductor"/>
      <property name="ki_keywords" value="inductor choke coil reactor magnetic"/>
      <sheetpath names="/" tstamps="/"/>
      <tstamps>e64ccd58-03c6-4151-ad43-f9c43d945096</tstamps>
    </comp>
    <comp ref="R1">
      <value>1k5</value>
      <footprint>Resistor_SMD:R_0603_1608Metric</footprint>
      <libsource lib="Device" part="R" description="Resistor"/>
      <property name="Sheetname" value=""/>
      <property name="Sheetfile" value="stm32-breakout.kicad_sch"/>
      <property name="ki_description" value="Resistor"/>
      <property name="ki_keywords" value="R res resistor"/>
      <sheetpath names="/" tstamps="/"/>
      <tstamps>3cc7a233-8d6e-43b4-8a8f-be59a606039d</tstamps>
    </comp>
    <comp ref="R2">
      <value>10k</value>
      <footprint>Resistor_SMD:R_0402_1005Metric</footprint>
      <libsource lib="Device" part="R" description="Resistor"/>
      <property name="Sheetname" value=""/>
      <property name="Sheetfile" value="stm32-breakout.kicad_sch"/>
      <property name="ki_description" value="Resistor"/>
      <property name="ki_keywords" value="R res resistor"/>
      <sheetpath names="/" tstamps="/"/>
      <tstamps>a1631a83-6d6f-4c3b-84ee-bffedb804dd5</tstamps>
    </comp>
    <comp ref="R3">
      <value>1k5</value>
      <footprint>Resistor_SMD:R_0603_1608Metric</footprint>
      <libsource lib="Device" part="R" description="Resistor"/>
      <property name="Sheetname" value=""/>
      <property name="Sheetfile" value="stm32-breakout.kicad_sch"/>
      <property name="ki_description" value="Resistor"/>
      <property name="ki_keywords" value="R res resistor"/>
      <sheetpath names="/" tstamps="/"/>
      <tstamps>b1b7d235-81a5-4e6d-a519-80e6a03ab1c3</tstamps>
    </comp>
    <comp ref="R4">
      <value>1k5</value>
      <footprint>Resistor_SMD:R_0402_1005Metric</footprint>
      <libsource lib="Device" part="R" description="Resistor"/>
      <property name="Sheetname" value=""/>
      <property name="Sheetfile" value="stm32-breakout.kicad_sch"/>
      <property name="ki_description" value="Resistor"/>
      <property name="ki_keywords" value="R res resistor"/>
      <sheetpath names="/" tstamps="/"/>
      <tstamps>80dc326d-ce28-4490-8a63-7d32c76375dc</tstamps>
    </comp>
    <comp ref="U1">
      <value>XC6206P333MR</value>
      <footprint>Package_TO_SOT_SMD:SOT-23-3</footprint>
      <datasheet>https://www.torexsemi.com/file/xc6206/XC6206.pdf</datasheet>
      <libsource lib="Regulator_Linear" part="XC6206PxxxMR" description="Positive 60-250mA Low Dropout Regulator, Fixed Output, SOT-23"/>
      <property name="Sheetname" value=""/>
      <property name="Sheetfile" value="stm32-breakout.kicad_sch"/>
      <property name="ki_description" value="Positive 60-250mA Low Dropout Regulator, Fixed Output, SOT-23"/>
      <property name="ki_keywords" value="Torex LDO Voltage Regulator Fixed Positive"/>
      <sheetpath names="/" tstamps="/"/>
      <tstamps>797a51d1-2ce1-4e6c-93de-87a1bdd83799</tstamps>
    </comp>
    <comp ref="U2">
      <value>STM32F103C8Tx</value>
      <footprint>Package_QFP:LQFP-48_7x7mm_P0.5mm</footprint>
      <datasheet>https://www.st.com/resource/en/datasheet/stm32f103c8.pdf</datasheet>
      <libsource lib="MCU_ST_STM32F1" part="STM32F103C8Tx" description="STMicroelectronics Arm Cortex-M3 MCU, 64KB flash, 20KB RAM, 72 MHz, 2.0-3.6V, 37 GPIO, LQFP48"/>
      <property name="Sheetname" value=""/>
      <property name="Sheetfile" value="stm32-breakout.kicad_sch"/>
      <property name="ki_description" value="STMicroelectronics Arm Cortex-M3 MCU, 64KB flash, 20KB RAM, 72 MHz, 2.0-3.6V, 37 GPIO, LQFP48"/>
      <property name="ki_keywords" value="Arm Cortex-M3 STM32F1 STM32F103"/>
      <sheetpath names="/" tstamps="/"/>
      <tstamps>55db639a-36a6-4cac-b438-c67a8e55ab76</tstamps>
    </comp>
    <comp ref="Y1">
      <value>8MHz</value>
      <footprint>Crystal:Crystal_SMD_5032-2Pin_5.0x3.2mm</footprint>
      <libsource lib="Device" part="Crystal_Small" description="Two pin crystal, small symbol"/>
      <property name="Sheetname" value=""/>
      <property name="Sheetfile" value="stm32-breakout.kicad_sch"/>
      <property name="ki_description" value="Two pin crystal, small symbol"/>
      <property name="ki_keywords" value="quartz ceramic resonator oscillator"/>
      <sheetpath names="/" tstamps="/"/>
      <tstamps>bb4de2ba-7f26-4e4a-b451-585d58bab463</tstamps>
    </comp>
  </components>
  <libparts>
    <libpart lib="Connector" part="USB_B_Micro">
      <description>USB Micro Type B connector</description>
      <docs>~</docs>
      <footprints>
        <fp>USB*</fp>
      </footprints>
      <fields>
        <field name="Reference">J</field>
        <field name="Value">USB_B_Micro</field>
        <field name="Datasheet">~</field>
      </fields>
      <pins>
        <pin num="1" name="VBUS" type="power_out"/>
        <pin num="2" name="D-" type="bidirectional"/>
        <pin num="3" name="D+" type="bidirectional"/>
        <pin num="4" name="ID" type="passive"/>
        <pin num="5" name="GND" type="power_out"/>
        <pin num="6" name="Shield" type="passive"/>
      </pins>
    </libpart>
    <libpart lib="Connector_Generic" part="Conn_01x15">
      <description>Generic connector, single row, 01x15, script generated (kicad-library-utils/schlib/autogen/connector/)</description>
      <docs>~</docs>
      <footprints>
        <fp>Connector*:*_1x??_*</fp>
      </footprints>
      <fields>
        <field name="Reference">J</field>
        <field name="Value">Conn_01x15</field>
        <field name="Datasheet">~</field>
      </fields>
      <pins>
        <pin num="1" name="Pin_1" type="passive"/>
        <pin num="2" name="Pin_2" type="passive"/>
        <pin num="3" name="Pin_3" type="passive"/>
        <pin num="4" name="Pin_4" type="passive"/>
        <pin num="5" name="Pin_5" type="passive"/>
        <pin num="6" name="Pin_6" type="passive"/>
        <pin num="7" name="Pin_7" type="passive"/>
        <pin num="8" name="Pin_8" type="passive"/>
        <pin num="9" name="Pin_9" type="passive"/>
        <pin num="10" name="Pin_10" type="passive"/>
        <pin num="11" name="Pin_11" type="passive"/>
        <pin num="12" name="Pin_12" type="passive"/>
        <pin num="13" name="Pin_13" type="passive"/>
        <pin num="14" name="Pin_14" type="passive"/>
        <pin num="15" name="Pin_15" type="passive"/>
      </pins>
    </libpart>
    <libpart lib="Device" part="C">
      <description>Unpolarized capacitor</description>
      <docs>~</docs>
      <footprints>
        <fp>C_*</fp>
      </footprints>
      <fields>
        <field name="Reference">C</field>
        <field name="Value">C</field>
        <field name="Datasheet">~</field>
      </fields>
      <pins>
        <pin num="1" name="" type="passive"/>
        <pin num="2" name="" type="passive"/>
      </pins>
    </libpart>
    <libpart lib="Device" part="Crystal_Small">
      <description>Two pin crystal, small symbol</description>
      <docs>~</docs>
      <footprints>
        <fp>Crystal*</fp>
      </footprints>
      <fields>
        <field name="Reference">Y</field>
        <field name="Value">Crystal_Small</field>
        <field name="Datasheet">~</field>
      </fields>
      <pins>
        <pin num="1" name="1" type="passive"/>
        <pin num="2" name="2" type="passive"/>
      </pins>
    </libpart>
    <libpart lib="Device" part="FerriteBead">
      <description>Ferrite bead</description>
      <docs>~</docs>
      <footprints>
        <fp>Inductor_*</fp>
        <fp>L_*</fp>
        <fp>*Ferrite*</fp>
      </footprints>
      <fields>
        <field name="Reference">FB</field>
        <field name="Value">FerriteBead</field>
        <field name="Datasheet">~</field>
      </fields>
      <pins>
        <pin num="1" name="" type="passive"/>
        <pin num="2" name="" type="passive"/>
      </pins>
    </libpart>
    <libpart lib="Device" part="L">
      <description>Inductor</description>
      <docs>~</docs>
      <footprints>
        <fp>Choke_*</fp>
        <fp>*Coil*</fp>
        <fp>Inductor_*</fp>
        <fp>L_*</fp>
      </footprints>
      <fields>
        <field name="Reference">L</field>
        <field name="Value">L</field>
        <field name="Datasheet">~</field>
      </fields>
      <pins>
        <pin num="1" name="1" type="passive"/>
        <pin num="2" name="2" type="passive"/>
      </pins>
    </libpart>
    <libpart lib="Device" part="LED_Small">
      <description>Light emitting diode, small symbol</description>
      <docs>~</docs>
      <footprints>
        <fp>LED*</fp>
        <fp>LED_SMD:*</fp>
        <fp>LED_THT:*</fp>
      </footprints>
      <fields>
        <field name="Reference">D</field>
        <field name="Value">LED_Small</field>
        <field name="Datasheet">~</field>
      </fields>
      <pins>
        <pin num="1" name="K" type="passive"/>
        <pin num="2" name="A" type="passive"/>
      </pins>
    </libpart>
    <libpart lib="Device" part="R">
      <description>Resistor</description>
      <docs>~</docs>
      <footprints>
        <fp>R_*</fp>
      </footprints>
      <fields>
        <field name="Reference">R</field>
        <field name="Value">R</field>
        <field name="Datasheet">~</field>
      </fields>
      <pins>
        <pin num="1" name="" type="passive"/>
        <pin num="2" name="" type="passive"/>
      </pins>
    </libpart>
    <libpart lib="Jumper" part="SolderJumper_2_Open">
      <description>Solder Jumper, 2-pole, open</description>
      <docs>~</docs>
      <footprints>
        <fp>SolderJumper*Open*</fp>
      </footprints>
      <fields>
        <field name="Reference">JP</field>
        <field name="Value">SolderJumper_2_Open</field>
        <field name="Datasheet">~</field>
      </fields>
      <pins>
        <pin num="1" name="A" type="passive"/>
        <pin num="2" name="B" type="passive"/>
      </pins>
    </libpart>
    <libpart lib="MCU_ST_STM32F1" part="STM32F103C8Tx">
      <description>STMicroelectronics Arm Cortex-M3 MCU, 64KB flash, 20KB RAM, 72 MHz, 2.0-3.6V, 37 GPIO, LQFP48</description>
      <docs>https://www.st.com/resource/en/datasheet/stm32f103c8.pdf</docs>
      <footprints>
        <fp>LQFP*7x7mm*P0.5mm*</fp>
      </footprints>
      <fields>
        <field name="Reference">U</field>
        <field name="Value">STM32F103C8Tx</field>
        <field name="Footprint">Package_QFP:LQFP-48_7x7mm_P0.5mm</field>
        <field name="Datasheet">https://www.st.com/resource/en/datasheet/stm32f103c8.pdf</field>
      </fields>
      <pins>
        <pin num="1" name="VBAT" type="power_in"/>
        <pin num="2" name="PC13" type="bidirectional"/>
        <pin num="3" name="PC14" type="bidirectional"/>
        <pin num="4" name="PC15" type="bidirectional"/>
        <pin num="5" name="PD0" type="bidirectional"/>
        <pin num="6" name="PD1" type="bidirectional"/>
        <pin num="7" name="NRST" type="input"/>
        <pin num="8" name="VSSA" type="power_in"/>
        <pin num="9" name="VDDA" type="power_in"/>
        <pin num="10" name="PA0" type="bidirectional"/>
        <pin num="11" name="PA1" type="bidirectional"/>
        <pin num="12" name="PA2" type="bidirectional"/>
        <pin num="13" name="PA3" type="bidirectional"/>
        <pin num="14" name="PA4" type="bidirectional"/>
        <pin num="15" name="PA5" type="bidirectional"/>
        <pin num="16" name="PA6" type="bidirectional"/>
        <pin num="17" name="PA7" type="bidirectional"/>
        <pin num="18" name="PB0" type="bidirectional"/>
        <pin num="19" name="PB1" type="bidirectional"/>
        <pin num="20" name="PB2" type="bidirectional"/>
        <pin num="21" name="PB10" type="bidirectional"/>
        <pin num="22" name="PB11" type="bidirectional"/>
        <pin num="23" name="VSS" type="power_in"/>
        <pin num="24" name="VDD" type="power_in"/>
        <pin num="25" name="PB12" type="bidirectional"/>
        <pin num="26" name="PB13" type="bidirectional"/>
        <pin num="27" name="PB14" type="bidirectional"/>
        <pin num="28" name="PB15" type="bidirectional"/>
        <pin num="29" name="PA8" type="bidirectional"/>
        <pin num="30" name="PA9" type="bidirectional"/>
        <pin num="31" name="PA10" type="bidirectional"/>
        <pin num="32" name="PA11" type="bidirectional"/>
        <pin num="33" name="PA12" type="bidirectional"/>
        <pin num="34" name="PA13" type="bidirectional"/>
        <pin num="35" name="VSS" type="passive"/>
        <pin num="36" name="VDD" type="power_in"/>
        <pin num="37" name="PA14" type="bidirectional"/>
        <pin num="38" name="PA15" type="bidirectional"/>
        <pin num="39" name="PB3" type="bidirectional"/>
        <pin num="40" name="PB4" type="bidirectional"/>
        <pin num="41" name="PB5" type="bidirectional"/>
        <pin num="42" name="PB6" type="bidirectional"/>
        <pin num="43" name="PB7" type="bidirectional"/>
        <pin num="44" name="BOOT0" type="input"/>
        <pin num="45" name="PB8" type="bidirectional"/>
        <pin num="46" name="PB9" type="bidirectional"/>
        <pin num="47" name="VSS" type="passive"/>
        <pin num="48" name="VDD" type="power_in"/>
      </pins>
    </libpart>
    <libpart lib="Mechanical" part="MountingHole">
      <description>Mounting Hole without connection</description>
      <docs>~</docs>
      <footprints>
        <fp>MountingHole*</fp>
      </footprints>
      <fields>
        <field name="Reference">H</field>
        <field name="Value">MountingHole</field>
        <field name="Datasheet">~</field>
      </fields>
    </libpart>
    <libpart lib="Regulator_Linear" part="XC6206PxxxMR">
      <description>Positive 60-250mA Low Dropout Regulator, Fixed Output, SOT-23</description>
      <docs>https://www.torexsemi.com/file/xc6206/XC6206.pdf</docs>
      <footprints>
        <fp>SOT?23?3*</fp>
      </footprints>
      <fields>
        <field name="Reference">U</field>
        <field name="Value">XC6206PxxxMR</field>
        <field name="Footprint">Package_TO_SOT_SMD:SOT-23-3</field>
        <field name="Datasheet">https://www.torexsemi.com/file/xc6206/XC6206.pdf</field>
      </fields>
      <pins>
        <pin num="1" name="GND" type="power_in"/>
        <pin num="2" name="VO" type="power_out"/>
        <pin num="3" name="VI" type="power_in"/>
      </pins>
    </libpart>
  </libparts>
  <libraries>
    <library logical="Connector">
      <uri>/usr/share/kicad/symbols//Connector.kicad_sym</uri>
    </library>
    <library logical="Connector_Generic">
      <uri>/usr/share/kicad/symbols//Connector_Generic.kicad_sym</uri>
    </library>
    <library logical="Device">
      <uri>/usr/share/kicad/symbols//Device.kicad_sym</uri>
    </library>
    <library logical="Jumper">
      <uri>/usr/share/kicad/symbols//Jumper.kicad_sym</uri>
    </library>
    <library logical="MCU_ST_STM32F1">
      <uri>/usr/share/kicad/symbols//MCU_ST_STM32F1.kicad_sym</uri>
    </library>
    <library logical="Mechanical">
      <uri>/usr/share/kicad/symbols//Mechanical.kicad_sym</uri>
    </library>
    <library logical="Regulator_Linear">
      <uri>/usr/share/kicad/symbols//Regulator_Linear.kicad_sym</uri>
    </library>
  </libraries>
  <nets>
    <net code="1" name="+3.3V">
      <node ref="C1" pin="1" pintype="passive"/>
      <node ref="C3" pin="1" pintype="passive"/>
      <node ref="C4" pin="1" pintype="passive"/>
      <node ref="C5" pin="1" pintype="passive"/>
      <node ref="C6" pin="1" pintype="passive"/>
      <node ref="C7" pin="1" pintype="passive"/>
      <node ref="D1" pin="2" pinfunction="A" pintype="passive"/>
      <node ref="J2" pin="1" pinfunction="Pin_1" pintype="passive"/>
      <node ref="J3" pin="1" pinfunction="Pin_1" pintype="passive"/>
      <node ref="JP1" pin="2" pinfunction="B" pintype="passive"/>
      <node ref="L1" pin="1" pinfunction="1" pintype="passive"/>
      <node ref="R4" pin="1" pintype="passive"/>
      <node ref="U1" pin="2" pinfunction="VO" pintype="power_out"/>
      <node ref="U2" pin="1" pinfunction="VBAT" pintype="power_in"/>
      <node ref="U2" pin="24" pinfunction="VDD" pintype="power_in"/>
      <node ref="U2" pin="36" pinfunction="VDD" pintype="power_in"/>
      <node ref="U2" pin="48" pinfunction="VDD" pintype="power_in"/>
    </net>
    <net code="2" name="+3.3VA">
      <node ref="C8" pin="1" pintype="passive"/>
      <node ref="C9" pin="1" pintype="passive"/>
      <node ref="L1" pin="2" pinfunction="2" pintype="passive"/>
      <node ref="U2" pin="9" pinfunction="VDDA" pintype="power_in"/>
    </net>
    <net code="3" name="+5V">
      <node ref="FB1" pin="1" pintype="passive"/>
      <node ref="J1" pin="1" pinfunction="VBUS" pintype="power_out"/>
    </net>
    <net code="4" name="/BOOT0">
      <node ref="JP1" pin="1" pinfunction="A" pintype="passive"/>
      <node ref="R2" pin="1" pintype="passive"/>
      <node ref="U2" pin="44" pinfunction="BOOT0" pintype="input"/>
    </net>
    <net code="5" name="/HSE_IN">
      <node ref="C11" pin="1" pintype="passive"/>
      <node ref="U2" pin="6" pinfunction="PD1" pintype="bidirectional"/>
      <node ref="Y1" pin="2" pinfunction="2" pintype="passive"/>
    </net>
    <net code="6" name="/HSE_OUT">
      <node ref="C10" pin="1" pintype="passive"/>
      <node ref="U2" pin="5" pinfunction="PD0" pintype="bidirectional"/>
      <node ref="Y1" pin="1" pinfunction="1" pintype="passive"/>
    </net>
    <net code="7" name="/LED_STAT">
      <node ref="D2" pin="2" pinfunction="A" pintype="passive"/>
      <node ref="U2" pin="11" pinfunction="PA1" pintype="bidirectional"/>
    </net>
    <net code="8" name="GND">
      <node ref="C1" pin="2" pintype="passive"/>
      <node ref="C10" pin="2" pintype="passive"/>
      <node ref="C11" pin="2" pintype="passive"/>
      <node ref="C2" pin="2" pintype="passive"/>
      <node ref="C3" pin="2" pintype="passive"/>
      <node ref="C4" pin="2" pintype="passive"/>
      <node ref="C5" pin="2" pintype="passive"/>
      <node ref="C6" pin="2" pintype="passive"/>
      <node ref="C7" pin="2" pintype="passive"/>
      <node ref="C8" pin="2" pintype="passive"/>
      <node ref="C9" pin="2" pintype="passive"/>
      <node ref="J1" pin="5" pinfunction="GND" pintype="power_out"/>
      <node ref="J2" pin="2" pinfunction="Pin_2" pintype="passive"/>
      <node ref="J3" pin="2" pinfunction="Pin_2" pintype="passive"/>
      <node ref="R1" pin="2" pintype="passive"/>
      <node ref="R2" pin="2" pintype="passive"/>
      <node ref="R3" pin="2" pintype="passive"/>
      <node ref="U1" pin="1" pinfunction="GND" pintype="power_in"/>
      <node ref="U2" pin="23" pinfunction="VSS" pintype="power_in"/>
      <node ref="U2" pin="35" pinfunction="VSS" pintype="passive"/>
      <node ref="U2" pin="47" pinfunction="VSS" pintype="passive"/>
      <node ref="U2" pin="8" pinfunction="VSSA" pintype="power_in"/>
    </net>
    <net code="9" name="Net-(D1-K)">
      <node ref="D1" pin="1" pinfunction="K" pintype="passive"/>
      <node ref="R1" pin="1" pintype="passive"/>
    </net>
    <net code="10" name="Net-(D2-K)">
      <node ref="D2" pin="1" pinfunction="K" pintype="passive"/>
      <node ref="R3" pin="1" pintype="passive"/>
    </net>
    <net code="11" name="PA3">
      <node ref="J3" pin="15" pinfunction="Pin_15" pintype="passive"/>
      <node ref="U2" pin="13" pinfunction="PA3" pintype="bidirectional"/>
    </net>
    <net code="12" name="PA4">
      <node ref="J3" pin="14" pinfunction="Pin_14" pintype="passive"/>
      <node ref="U2" pin="14" pinfunction="PA4" pintype="bidirectional"/>
    </net>
    <net code="13" name="PA5">
      <node ref="J3" pin="13" pinfunction="Pin_13" pintype="passive"/>
      <node ref="U2" pin="15" pinfunction="PA5" pintype="bidirectional"/>
    </net>
    <net code="14" name="PA6">
      <node ref="J3" pin="12" pinfunction="Pin_12" pintype="passive"/>
      <node ref="U2" pin="16" pinfunction="PA6" pintype="bidirectional"/>
    </net>
    <net code="15" name="PA7">
      <node ref="J3" pin="11" pinfunction="Pin_11" pintype="passive"/>
      <node ref="U2" pin="17" pinfunction="PA7" pintype="bidirectional"/>
    </net>
    <net code="16" name="PA8">
      <node ref="J3" pin="5" pinfunction="Pin_5" pintype="passive"/>
      <node ref="U2" pin="29" pinfunction="PA8" pintype="bidirectional"/>
    </net>
    <net code="17" name="PA9">
      <node ref="J3" pin="4" pinfunction="Pin_4" pintype="passive"/>
      <node ref="U2" pin="30" pinfunction="PA9" pintype="bidirectional"/>
    </net>
    <net code="18" name="PA10">
      <node ref="J3" pin="3" pinfunction="Pin_3" pintype="passive"/>
      <node ref="U2" pin="31" pinfunction="PA10" pintype="bidirectional"/>
    </net>
    <net code="19" name="PA15">
      <node ref="J2" pin="5" pinfunction="Pin_5" pintype="passive"/>
      <node ref="U2" pin="38" pinfunction="PA15" pintype="bidirectional"/>
    </net>
    <net code="20" name="PB0">
      <node ref="J3" pin="10" pinfunction="Pin_10" pintype="passive"/>
      <node ref="U2" pin="18" pinfunction="PB0" pintype="bidirectional"/>
    </net>
    <net code="21" name="PB1">
      <node ref="J3" pin="9" pinfunction="Pin_9" pintype="passive"/>
      <node ref="U2" pin="19" pinfunction="PB1" pintype="bidirectional"/>
    </net>
    <net code="22" name="PB2">
      <node ref="J3" pin="8" pinfunction="Pin_8" pintype="passive"/>
      <node ref="U2" pin="20" pinfunction="PB2" pintype="bidirectional"/>
    </net>
    <net code="23" name="PB4">
      <node ref="J2" pin="7" pinfunction="Pin_7" pintype="passive"/>
      <node ref="U2" pin="40" pinfunction="PB4" pintype="bidirectional"/>
    </net>
    <net code="24" name="PB5">
      <node ref="J2" pin="8" pinfunction="Pin_8" pintype="passive"/>
      <node ref="U2" pin="41" pinfunction="PB5" pintype="bidirectional"/>
    </net>
    <net code="25" name="PB6">
      <node ref="J2" pin="9" pinfunction="Pin_9" pintype="passive"/>
      <node ref="U2" pin="42" pinfunction="PB6" pintype="bidirectional"/>
    </net>
    <net code="26" name="PB7">
      <node ref="J2" pin="10" pinfunction="Pin_10" pintype="passive"/>
      <node ref="U2" pin="43" pinfunction="PB7" pintype="bidirectional"/>
    </net>
    <net code="27" name="PB8">
      <node ref="J2" pin="11" pinfunction="Pin_11" pintype="passive"/>
      <node ref="U2" pin="45" pinfunction="PB8" pintype="bidirectional"/>
    </net>
    <net code="28" name="PB9">
      <node ref="J2" pin="12" pinfunction="Pin_12" pintype="passive"/>
      <node ref="U2" pin="46" pinfunction="PB9" pintype="bidirectional"/>
    </net>
    <net code="29" name="PB10">
      <node ref="J3" pin="7" pinfunction="Pin_7" pintype="passive"/>
      <node ref="U2" pin="21" pinfunction="PB10" pintype="bidirectional"/>
    </net>
    <net code="30" name="PB11">
      <node ref="J3" pin="6" pinfunction="Pin_6" pintype="passive"/>
      <node ref="U2" pin="22" pinfunction="PB11" pintype="bidirectional"/>
    </net>
    <net code="31" name="PC13">
      <node ref="J2" pin="13" pinfunction="Pin_13" pintype="passive"/>
      <node ref="U2" pin="2" pinfunction="PC13" pintype="bidirectional"/>
    </net>
    <net code="32" name="PC14">
      <node ref="J2" pin="14" pinfunction="Pin_14" pintype="passive"/>
      <node ref="U2" pin="3" pinfunction="PC14" pintype="bidirectional"/>
    </net>
    <net code="33" name="PC15">
      <node ref="J2" pin="15" pinfunction="Pin_15" pintype="passive"/>
      <node ref="U2" pin="4" pinfunction="PC15" pintype="bidirectional"/>
    </net>
    <net code="34" name="SW0">
      <node ref="J2" pin="6" pinfunction="Pin_6" pintype="passive"/>
      <node ref="U2" pin="39" pinfunction="PB3" pintype="bidirectional"/>
    </net>
    <net code="35" name="SWCLK">
      <node ref="J2" pin="4" pinfunction="Pin_4" pintype="passive"/>
      <node ref="U2" pin="37" pinfunction="PA14" pintype="bidirectional"/>
    </net>
    <net code="36" name="SWDIO">
      <node ref="J2" pin="3" pinfunction="Pin_3" pintype="passive"/>
      <node ref="U2" pin="34" pinfunction="PA13" pintype="bidirectional"/>
    </net>
    <net code="37" name="USB_D+">
      <node ref="J1" pin="3" pinfunction="D+" pintype="bidirectional"/>
      <node ref="R4" pin="2" pintype="passive"/>
      <node ref="U2" pin="33" pinfunction="PA12" pintype="bidirectional"/>
    </net>
    <net code="38" name="USB_D-">
      <node ref="J1" pin="2" pinfunction="D-" pintype="bidirectional"/>
      <node ref="U2" pin="32" pinfunction="PA11" pintype="bidirectional"/>
    </net>
    <net code="39" name="VCC">
      <node ref="C2" pin="1" pintype="passive"/>
      <node ref="FB1" pin="2" pintype="passive"/>
      <node ref="U1" pin="3" pinfunction="VI" pintype="power_in"/>
    </net>
    <net code="40" name="unconnected-(J1-ID-Pad4)">
      <node ref="J1" pin="4" pinfunction="ID" pintype="passive+no_connect"/>
    </net>
    <net code="41" name="unconnected-(J1-Shield-Pad6)">
      <node ref="J1" pin="6" pinfunction="Shield" pintype="passive+no_connect"/>
    </net>
    <net code="42" name="unconnected-(U2-NRST-Pad7)">
      <node ref="U2" pin="7" pinfunction="NRST" pintype="input+no_connect"/>
    </net>
    <net code="43" name="unconnected-(U2-PA0-Pad10)">
      <node ref="U2" pin="10" pinfunction="PA0" pintype="bidirectional+no_connect"/>
    </net>
    <net code="44" name="unconnected-(U2-PA2-Pad12)">
      <node ref="U2" pin="12" pinfunction="PA2" pintype="bidirectional+no_connect"/>
    </net>
    <net code="45" name="unconnected-(U2-PB12-Pad25)">
      <node ref="U2" pin="25" pinfunction="PB12" pintype="bidirectional+no_connect"/>
    </net>
    <net code="46" name="unconnected-(U2-PB13-Pad26)">
      <node ref="U2" pin="26" pinfunction="PB13" pintype="bidirectional+no_connect"/>
    </net>
    <net code="47" name="unconnected-(U2-PB14-Pad27)">
      <node ref="U2" pin="27" pinfunction="PB14" pintype="bidirectional+no_connect"/>
    </net>
    <net code="48" name="unconnected-(U2-PB15-Pad28)">
      <node ref="U2" pin="28" pinfunction="PB15" pintype="bidirectional+no_connect"/>
    </net>
  </nets>
</export>
